{
    " id": {
      "uniquekey":"anything",
      "title":"text",
      "description":"text",
      "image_url":"https://",
      "providerName":"text",
      "providerUrl":"url",
      "authorName":"text",
      "authorUrl":"url",
      "color":"#fff"
      
    },
   "guard": {
      "uniquekey":"guard",
      "title":"guardontop",
      "description":"guardscripts free original scripts",
      "image_url":"https://guard.lol/videos/pointlaugh.png",
      "providerName":"provname",
      "providerUrl":"https://guard.lol",
      "authorName":"text",
      "authorUrl":"https://guard.lol?auth=em",
      "color":"#000000"
    },
    
    "notice": {
      "uniquekey":"notice",
      "title":"This isn't a game exploit this is a server that makes scripts for fun and free only.",
      "description":"THIS DOES NOT BREAK ROBLOX'S TOS OR DISCORD'S. THIS IS NOT A CHEAT, THESE ARE SCRIPTS. WE DON'T TAKE RESPONSIBILITY FOR OUR CLIENTS CHOOSE WHAT THEY WANT TO DO WITH IT. THE SCRIPTS INTENDED USE IS TO BE USED FOR ROBLOX STUDIO NOT A THIRD PARTY SOFTWARE. THIS IS NOT A CHEAT/EXPLOIT. ONCE AGAIN OUR CLIENTS CHOOSE WHAT THEY WANT TO DO WITH IT.",
      "providerName":"Read this notice regarding the service provided in this server.",
      "providerUrl":"https://guard.lol/notice",
      "color":"#347deb"
    },
    "":"↓ ↓"
}
